panelexpr/__init__.py
panelexpr/interface.py
panelexpr/base/__init__.py
panelexpr/base/context.py
panelexpr/base/exprtree.py
panelexpr/base/node.py
panelexpr/base/operator.py
panelexpr/base/parser.py
panelexpr/boost/__init__.py
panelexpr/boost/calc.py
panelexpr-0.1.0.dist-info/LICENSE.txt
panelexpr-0.1.0.dist-info/METADATA
panelexpr-0.1.0.dist-info/WHEEL
panelexpr-0.1.0.dist-info/top_level.txt
panelexpr-0.1.0.dist-info/RECORD
