Metadata-Version: 2.1
Name: panelexpr
Version: 0.1.0
Summary: A panel data evaluator.
Home-page: https://github.com/actcwlf/panelexpr
Author: actcwlf
Author-email: actcwlf@qq.com
License: MIT
Platform: UNKNOWN
Classifier: Development Status :: 4 - Beta
Classifier: Programming Language :: Python :: 3
Classifier: License :: OSI Approved :: MIT License
Classifier: Operating System :: OS Independent
Requires-Python: >=3.6
Requires-Dist: pandas (>=0.20.0)
Requires-Dist: numpy (>=1.14.0)
Requires-Dist: numba (>=0.45.0)
Requires-Dist: numexpr (>=2.7.0)
